Metadata-Version: 2.1
Name: htmlparsers
Version: 0.0.1
Summary: A collection of classes to parse HTML as JSON from famous sources like Google Search, Bing Search, LinkedIn and others.
Home-page: https://rehmat.works
Author: Rehmat Alam
Author-email: contact@rehmat.works
License: GPL3
Platform: UNKNOWN
